exifkill/__init__.py
exifkill/__main__.py
exifkill-0.1.0.dist-info/COPYING
exifkill-0.1.0.dist-info/METADATA
exifkill-0.1.0.dist-info/WHEEL
exifkill-0.1.0.dist-info/RECORD
